thormotion-0.4.2.dist-info/METADATA
thormotion-0.4.2.dist-info/WHEEL
thormotion-0.4.2.dist-info/licenses/LICENSE
thormotion/__init__.py
thormotion/thormotion.pypy311-pp73-aarch64-linux-gnu.so
thormotion-0.4.2.dist-info/RECORD
