Metadata-Version: 2.4
Name: thormotion
Version: 0.4.2
Classifier: Programming Language :: Rust
Classifier: Programming Language :: Python :: Implementation :: CPython
Classifier: Programming Language :: Python :: Implementation :: PyPy
License-File: LICENSE
Summary: A cross-platform motion control library for Thorlabs systems, written in Rust.
Author: Amelia Fraser-Dale
License: BSD-3-Clause
Requires-Python: >=3.8
